pack_yt/__init__.py
pack_yt/main.py
pack_yt/setting.py
pack_yt/utils.py
pack_yt/yt_log.py
pack_yt/model/__init__.py
pack_yt/model/found.py
pack_yt/model/yt.py
pack_yt/pipeline/__init__.py
pack_yt/pipeline/pipeline.py
pack_yt/pipeline/steps/__init__.py
pack_yt/pipeline/steps/building.py
pack_yt/pipeline/steps/download_video.py
pack_yt/pipeline/steps/downloadcaption.py
pack_yt/pipeline/steps/edit_video.py
pack_yt/pipeline/steps/getvideolist.py
pack_yt/pipeline/steps/initializeyt.py
pack_yt/pipeline/steps/postflight.py
pack_yt/pipeline/steps/readcaption.py
pack_yt/pipeline/steps/searchword.py
pack_yt/pipeline/steps/step.py
packyt-0.1.0.dist-info/LICENSE
packyt-0.1.0.dist-info/METADATA
packyt-0.1.0.dist-info/WHEEL
packyt-0.1.0.dist-info/top_level.txt
packyt-0.1.0.dist-info/RECORD
