Metadata-Version: 2.1
Name: packyt
Version: 0.1.0
Summary: concate videos
Home-page: https://github.com/aws753951/packyt
Author: Marc Zhu
Author-email: a0983204766@gmail.com
License: MIT
Platform: UNKNOWN
Classifier: License :: OSI Approved :: MIT License
Classifier: Programming Language :: Python
Classifier: Programming Language :: Python :: 3
Classifier: Programming Language :: Python :: 3.6
Classifier: Programming Language :: Python :: Implementation :: CPython
Classifier: Programming Language :: Python :: Implementation :: PyPy
Requires-Python: >=3.10.0
License-File: LICENSE
Requires-Dist: moviepy
Requires-Dist: python-dotenv
Requires-Dist: pytube
Requires-Dist: requests
Requires-Dist: urllib3
